LICENSE
MANIFEST.in
README.md
setup.py
SQLAlchemy_JSONAPI.egg-info/PKG-INFO
SQLAlchemy_JSONAPI.egg-info/SOURCES.txt
SQLAlchemy_JSONAPI.egg-info/dependency_links.txt
SQLAlchemy_JSONAPI.egg-info/not-zip-safe
SQLAlchemy_JSONAPI.egg-info/requires.txt
SQLAlchemy_JSONAPI.egg-info/top_level.txt
sqlalchemy_jsonapi/__init__.py
sqlalchemy_jsonapi/_version.py
sqlalchemy_jsonapi/constants.py
sqlalchemy_jsonapi/errors.py
sqlalchemy_jsonapi/flaskext.py
sqlalchemy_jsonapi/serializer.py