Metadata-Version: 1.1
Name: SQLAlchemy-JSONAPI
Version: 4.0.10
Summary: JSONAPI Mixin for SQLAlchemy
Home-page: http://github.com/coltonprovias/sqlalchemy-jsonapi
Author: Colton J. Provias
Author-email: cj@coltonprovias.com
License: MIT
Platform: any
Classifier: Development Status :: 5 - Production/Stable
Classifier: Environment :: Web Environment
Classifier: Framework :: Flask
Classifier: Intended Audience :: Developers
Classifier: License :: OSI Approved :: MIT License
Classifier: Natural Language :: English
Classifier: Operating System :: OS Independent
Classifier: Programming Language :: Python :: 3.4
Classifier: Programming Language :: Python :: 3.5
Classifier: Topic :: Software Development :: Libraries :: Python Modules
